meme/__init__.py
meme/__main__.py
meme/meme.py
meme_lang-1.0.2.dist-info/METADATA
meme_lang-1.0.2.dist-info/WHEEL
meme_lang-1.0.2.dist-info/entry_points.txt
meme_lang-1.0.2.dist-info/top_level.txt
meme_lang-1.0.2.dist-info/RECORD
