Metadata-Version: 2.1
Name: meme-lang
Version: 1.0.2
Summary: Package for meme language
Home-page: https://github.com/LighghtEeloo/meme-lang
Author: LighghtEeloo
Author-email: litiaeeloo@gmail.com
License: UNKNOWN
Project-URL: Bug Tracker, https://github.com/LighghtEeloo/meme-lang/issues
Platform: UNKNOWN
Classifier: Programming Language :: Python :: 3
Classifier: License :: OSI Approved :: MIT License
Classifier: Operating System :: OS Independent
Requires-Python: >=3.6
Requires-Dist: click
